Metadata-Version: 2.1
Name: oshash
Version: 0.1.1
Summary: Open Subtitles Hash implementation
Home-page: https://github.com/r-salas/oshash
Author: Rubén Salas
License: GNU General Public License v3.0
Platform: UNKNOWN
Classifier: Programming Language :: Python :: 3
Classifier: Operating System :: OS Independent
Classifier: Intended Audience :: Developers
Requires-Python: >=3.5
